odoo/addons/ssi_voucher_giro/README.rst
odoo/addons/ssi_voucher_giro/__init__.py
odoo/addons/ssi_voucher_giro/__manifest__.py
odoo/addons/ssi_voucher_giro/menu.xml
odoo/addons/ssi_voucher_giro/data/account_voucher_type_data.xml
odoo/addons/ssi_voucher_giro/data/approval_template_giro_payment_data.xml
odoo/addons/ssi_voucher_giro/data/approval_template_giro_receipt_data.xml
odoo/addons/ssi_voucher_giro/data/ir_sequence_data.xml
odoo/addons/ssi_voucher_giro/data/ir_windows_action_data.xml
odoo/addons/ssi_voucher_giro/data/policy_template_giro_payment_data.xml
odoo/addons/ssi_voucher_giro/data/policy_template_giro_receipt_data.xml
odoo/addons/ssi_voucher_giro/data/sequence_template_giro_payment_data.xml
odoo/addons/ssi_voucher_giro/data/sequence_template_giro_receipt_data.xml
odoo/addons/ssi_voucher_giro/models/__init__.py
odoo/addons/ssi_voucher_giro/models/giro_payment.py
odoo/addons/ssi_voucher_giro/models/giro_receipt.py
odoo/addons/ssi_voucher_giro/models/mixin_giro_voucher.py
odoo/addons/ssi_voucher_giro/security/ir.model.access.csv
odoo/addons/ssi_voucher_giro/security/ir_module_category_data.xml
odoo/addons/ssi_voucher_giro/security/ir_rule_data.xml
odoo/addons/ssi_voucher_giro/security/res_group_data.xml
odoo/addons/ssi_voucher_giro/static/description/banner.png
odoo/addons/ssi_voucher_giro/static/description/icon.png
odoo/addons/ssi_voucher_giro/views/account_giro_payment_views.xml
odoo/addons/ssi_voucher_giro/views/account_giro_receipt_views.xml
odoo/addons/ssi_voucher_giro/views/account_giro_voucher_views.xml
odoo14_addon_ssi_voucher_giro-14.0.2.2.0.dist-info/METADATA
odoo14_addon_ssi_voucher_giro-14.0.2.2.0.dist-info/WHEEL
odoo14_addon_ssi_voucher_giro-14.0.2.2.0.dist-info/top_level.txt
odoo14_addon_ssi_voucher_giro-14.0.2.2.0.dist-info/RECORD
